honeyshare/__init__.py
honeyshare/api/__init__.py
honeyshare/api/api_common.py
honeyshare/api/blacklist.py
honeyshare/api/hostname.py
honeyshare/api/ipv4.py
honeyshare/api/port.py
honeyshare/api/timeseries.py
honeyshare/api/util.py
honeyshare/api_requests.py
honeyshare/bytes_functions.py
honeyshare/config.py
honeyshare/honeyshare.py
honeyshare-1.5.1.dist-info/LICENSE
honeyshare-1.5.1.dist-info/METADATA
honeyshare-1.5.1.dist-info/WHEEL
honeyshare-1.5.1.dist-info/RECORD
