Metadata-Version: 2.3
Name: honeyshare
Version: 1.5.1
Summary: Python API client for HoneyShare.live
License: MIT
Author: Pedro Melgueira
Author-email: pedro@honeyshare.live
Requires-Python: >=3.10,<4.0
Classifier: License :: OSI Approved :: MIT License
Classifier: Programming Language :: Python :: 3
Classifier: Programming Language :: Python :: 3.10
Classifier: Programming Language :: Python :: 3.11
Classifier: Programming Language :: Python :: 3.12
Classifier: Programming Language :: Python :: 3.13
Requires-Dist: requests (>=2.32.4,<3.0.0)
